clarity_gate/__init__.py
clarity_gate/cli.py
clarity_gate/types.py
clarity_gate/compute/__init__.py
clarity_gate/compute/body_hash.py
clarity_gate/compute/ingestable.py
clarity_gate/parser/__init__.py
clarity_gate/parser/end_marker.py
clarity_gate/parser/exclusions.py
clarity_gate/parser/normalize.py
clarity_gate/parser/yaml_parser.py
clarity_gate/validators/__init__.py
clarity_gate/validators/cgd.py
clarity_gate/validators/sot.py
clarity_gate-1.0.0.dist-info/METADATA
clarity_gate-1.0.0.dist-info/WHEEL
clarity_gate-1.0.0.dist-info/entry_points.txt
clarity_gate-1.0.0.dist-info/RECORD
