Metadata-Version: 2.4
Name: clarity-gate
Version: 1.0.0
Summary: Pre-ingestion verification for epistemic quality in RAG systems
Project-URL: Homepage, https://github.com/frmoretto/clarity-gate
Project-URL: Documentation, https://github.com/frmoretto/clarity-gate/docs
Project-URL: Repository, https://github.com/frmoretto/clarity-gate
Project-URL: Issues, https://github.com/frmoretto/clarity-gate/issues
Author: Francesco Marinoni Moretto
License-Expression: CC-BY-4.0
Keywords: ai-safety,cgd,clarity-gate,document-quality,epistemic,hallucination,llm,pre-ingestion,rag,sot,source-of-truth,validator,verification
Classifier: Development Status :: 4 - Beta
Classifier: Intended Audience :: Developers
Classifier: License :: OSI Approved
Classifier: Operating System :: OS Independent
Classifier: Programming Language :: Python :: 3
Classifier: Programming Language :: Python :: 3.9
Classifier: Programming Language :: Python :: 3.10
Classifier: Programming Language :: Python :: 3.11
Classifier: Programming Language :: Python :: 3.12
Classifier: Topic :: Software Development :: Quality Assurance
Classifier: Topic :: Text Processing :: Markup
Classifier: Typing :: Typed
Requires-Python: >=3.9
Requires-Dist: pyyaml>=6.0
Provides-Extra: dev
Requires-Dist: mypy>=1.0; extra == 'dev'
Requires-Dist: pytest-cov>=4.0; extra == 'dev'
Requires-Dist: pytest>=7.0; extra == 'dev'
Requires-Dist: ruff>=0.1.0; extra == 'dev'
